LICENSE
MANIFEST.in
README.md
VERSION
setup.py
periflow_sdk/__init__.py
periflow_sdk/errors.py
periflow_sdk/manager.py
periflow_sdk/utils.py
periflow_sdk.egg-info/PKG-INFO
periflow_sdk.egg-info/SOURCES.txt
periflow_sdk.egg-info/dependency_links.txt
periflow_sdk.egg-info/requires.txt
periflow_sdk.egg-info/top_level.txt
periflow_sdk/comm/__init__.py
periflow_sdk/comm/errors.py
periflow_sdk/comm/ipc.py
periflow_sdk/dataloading/__init__.py
periflow_sdk/dataloading/dataloader.py
periflow_sdk/dataloading/sampler.py